Workbook

Sheet Cover
B2: LEVFIN OPTIONS VALUATION MODEL
B3: Pricing the Embedded Options in Leveraged Loans and High Yield Bonds
B5: Federico Etchelecu · May 2026
B6: Companion to: The Optionality of Credit Agreements (Treatise)
B7: Version 2.2 · Recalibrated builder + sensitivity sheet
B9: MODEL OVERVIEW
B10: This workbook implements the options-pricing framework laid out in Chapter 13 of the treatise. Every embedded option class is priced on its own worksheet with live Excel formulas. Default inputs are set to the Grifols credit.
B13: SHEETS
B14: 1. Inputs | C14: Deal-level inputs: enterprise value, debt face, asset vol, EBITDA, rates
B15: 2. Merton Credit Put | C15: Merton (1974) structural model; implied credit spread
B16: 3. Call Schedule (HY) | C16: Make-whole and fixed call schedule for a HY bond
B17: 4. Debt Incurrence | C17: Free-and-clear, ratio-based incremental, MFN
B18: 5. Restricted Payments | C18: Starter, leverage-based RP, builder basket
B19: 6. Asset Sale Bundle | C19: Reinvestment right and leverage-based step-downs
B20: 7. CoC & Portability | C20: Change-of-control put, portability, disguised portability
B21: 8. Equity Cure | C21: Bermudan put on quarterly EBITDA tests
B22: 9. Springing Cov + MFN | C22: Knock-in barrier on RCF utilization; MFN lookback
B23: 10. LME Bundle | C23: Anti-Serta and anti-J.Crew protection value
B24: 11. Master Summary | C24: All options aggregated; fair spread vs. market spread
B25: 12. Sensitivity | C25: One-way tornado: total optionality vs flexed inputs
B27: CALIBRATION NOTES (v2)
B28: • Basket value → spread cost: scaled by issue size + duration, not divided by tenor.
B29: • All 'short to lender' values are negative; 'long to lender' protections positive.
B30: • MAX(0, ...) clamps applied to prevent negative-headroom inversion.
B31: • Equity cure recovery improvement set to 10% (was 20%) — more realistic.
B32: • Builder basket scaled by Asian-damping × exercise probability × marginal spread.
B33: • Default inputs are set to the Grifols credit; outputs are directional only.
B35: WORKED EXAMPLE
B36: This workbook is a parametric companion: its closed-form and binomial estimates are directional and price a wider option set than the Monte Carlo decomposition. Grifols_Model_v8.xlsx is the source of record for the Grifols figures — see Chapter 18.

Sheet Inputs
B1: DEAL INPUTS — drives all downstream sheets
B3: ENTERPRISE & CAPITAL STRUCTURE
B4: Enterprise Value V_0 (EUR m) | C4: 18194 | D4: Grifols — mean enterprise value, integrated model
B5: Super-Senior RCF face (EUR m) | C5: 1000
B6: First-Lien TLB face (EUR m) | C6: 6180
B7: HY SSN bonds face (EUR m) | C7: 1386
B8: Total Debt | C8: =SUM(C5:C7) -> 8566
B9: LTM EBITDA (EUR m) | C9: 1693 | D9: FY2025A reported (per Grifols_Model_v8); was 1687
B10: Opening leverage (drawn; RCF undrawn) | C10: =(C6+C7)/C9 -> 4.46899 | D10: RCF undrawn at close, excluded from drawn leverage; Grifols credit at ~4.8x
B12: VOLATILITY & DEFAULT PARAMETERS
B13: Asset volatility σ_V | C13: 0.08 | D13: From sector benchmarks / equity vol deflation
B14: EBITDA volatility σ_EBITDA | C14: 0.08
B15: EBITDA mean-reversion κ | C15: 0.4
B16: Default hazard rate λ_default | C16: 0.05
B17: Recovery rate (1st-lien) | C17: 0.65
B19: RATES & TIMING
B20: Risk-free rate (SOFR/€STR) | C20: 0.045
B21: Tenor (years) | C21: 5
B22: Market spread on TLB (bps) | C22: 248
B23: Market coupon on HY | C23: 0.054
B25: EVENT HAZARDS
B26: CoC hazard λ_CoC (annual) | C26: 0.18
B27: IPO hazard λ_IPO (annual) | C27: 0.04
B28: Permitted Holders dilution | C28: 0.4 | D28: Share of buyers covered by Permitted Holders def
B30: DERIVED — sanity checks
B31: Total leverage | C31: =C10 -> 4.46899
B32: First-lien leverage (RCF+TLB)/EBITDA | C32: =(C5+C6)/C9 -> 4.2409923
B33: LTV (Debt / EV) | C33: =C8/C4 -> 0.47081455
B35: BPS CONVENTION (v2.1)
B36: All option costs/gains are quoted as annualised running bps over (Total Debt × Tenor).
B37: HY-only options (calls, CoC, portability) computed on HY base; Master Summary face-weights them to deal level.

Sheet Merton Credit Put
B1: MERTON STRUCTURAL CREDIT-RISK PUT
B2: Equity as a call on enterprise value; debt as bond minus put.
B4: MODEL INPUTS
B5: Enterprise Value V_0 (EUR m) | C5: =Inputs!C4 -> 18194
B6: Total Debt face F (EUR m) | C6: =Inputs!C8 -> 8566
B7: Asset volatility σ_V | C7: =Inputs!C13 -> 0.08
B8: Risk-free rate r | C8: =Inputs!C20 -> 0.045
B9: Tenor T (years) | C9: =Inputs!C21 -> 5
B11: BLACK-SCHOLES COMPUTATIONS
B12: d1 = [ln(V/F) + (r + σ²/2)T] / (σ√T) | C12: =(LN(C5/C6)+(C8+C7^2/2)*C9)/(C7*SQRT(C9)) -> 5.5582556
B13: d2 = d1 - σ√T | C13: =C12-C7*SQRT(C9) -> 5.3793702
B14: N(d1) | C14: =NORMSDIST(C12) -> 0.99999999
B15: N(d2) | C15: =NORMSDIST(C13) -> 0.99999996
B16: N(-d1) | C16: =NORMSDIST(-C12) -> 1.3624207e-08
B17: N(-d2) | C17: =NORMSDIST(-C13) -> 3.7373438e-08
B19: RESULTS
B20: Equity value = V·N(d1) - F·exp(-rT)·N(d2) | C20: =C5*C14-C6*EXP(-C8*C9)*C15 -> 11353.91
B21: Risk-free debt PV = F·exp(-rT) | C21: =C6*EXP(-C8*C9) -> 6840.0899
B22: Credit-risk put = F·exp(-rT)·N(-d2) - V·N(-d1) | C22: =C21*C17-C5*C16 -> 7.7588487e-06
B23: Risky debt value = risk-free PV - put | C23: =C21-C22 -> 6840.0899
B25: Merton-implied credit spread (bps) | C25: =(-LN(C23/C6)/C9-C8)*10000 -> 2.2686391e-06
B26: Adjusted for jumps & early-default (+factor) | C26: 2.1 | D26: Vanilla Merton underprices B credits (ignores jumps + early default). 1.5-2.5x typical; 2.1 calibrated to the Ch.15 worked example.
B27: Adjusted Merton spread (bps) | C27: =C25*C26 -> 4.7641421e-06
B28: Market TLB spread (bps) | C28: =Inputs!C22 -> 248
B29: Credit-risk component (Merton, bps) | C29: =C27 -> 4.7641421e-06
B31: Note: vanilla Merton underprices B-rated credits because it ignores jumps
B32: and the Black-Cox early-default barrier. Adjustment factor of ~1.8 calibrates
B33: to typical B2/B observed spreads. Reduce to 1.0 to see pure Merton.

Sheet Call Schedule (HY)
B1: HY BOND CALL SCHEDULE
B3: INPUTS
B4: Bond face (EUR m) | C4: =Inputs!C7 -> 1386
B5: Coupon | C5: =Inputs!C23 -> 0.054
B6: Tenor | C6: =Inputs!C21 -> 5
B7: Non-call period | C7: 3
B8: Make-whole spread over T (bps) | C8: 50
B9: Issuer credit spread (bps) | C9: 350
B11: FIXED CALL SCHEDULE
B12: Year 4 call price | C12: 1.05
B13: Year 5 call price | C13: 1.025
B14: Year 6 call price | C14: 1.0125
B15: Year 7 call price | C15: 1
B17: RESULTS
B18: Prob. of exercise (4-7y window) | C18: =1-EXP(-Inputs!C16*4) -> 0.18126925
B19: Avg call premium (weighted) | C19: =AVERAGE(C12:C15)-1 -> 0.021875
B20: Fixed-call lender loss (bps) | C20: =-C18*C19*10000/Inputs!C21 -> -7.9305296
B22: Make-whole discount rate (T + spread) | C22: =Inputs!C20+C8/10000 -> 0.05
B23: Bond YTM (R + issuer spread) | C23: =Inputs!C20+C9/10000 -> 0.08
B24: MW prob. of exercise during NC | C24: 0.35
B25: Make-whole option value (bps spread) | C25: =-MAX(0,C23-C22)*10000*C24*0.5 -> -52.5
B26: Note: MW value capped at ~half the spread differential × exercise prob

Sheet Debt Incurrence
B1: DEBT-INCURRENCE OPTIONS
B3: FREE-AND-CLEAR BASKET (American call)
B4: Basket size (EUR m) | C4: 175
B5: Marginal cost-of-debt spread above current (bps) | C5: 100
B6: Tenor of new debt | C6: 5
B7: Probability of exercise within tenor | C7: 0.55
B8: Value to borrower (EUR m) | C8: =C4*C5/10000*C6*C7 -> 4.8125
B9: Spread cost to lender (bps) | C9: =-C8*10000/Inputs!C8/Inputs!C21 -> -1.1236283
B10: Annualised over full tenor on total debt face (v2.1 convention)
B12: RATIO-BASED INCREMENTAL
B13: Leverage incurrence ceiling (x) | C13: 6
B14: Current leverage | C14: =Inputs!C10 -> 4.46899
B15: Leverage headroom (turns) | C15: =MAX(0,C13-C14) -> 1.53101
B16: EBITDA volatility | C16: =Inputs!C14 -> 0.08
B17: Prob. of usable headroom over tenor | C17: =IF(C15>0,NORMSDIST(C15/(C16*SQRT(Inputs!C21))),NORMSDIST(-ABS(C15)/(C16*SQRT(Inputs!C21)))) -> 1
B18: Max incremental debt at ceiling (EUR m) | C18: =MAX(0,C15)*Inputs!C9+IF(C15<=0,Inputs!C9*0.5,0) -> 2592
B19: If currently above ceiling, future deleveraging could open capacity
B20: Probability-weighted value to borrower | C20: =C17*C18*C5/10000*C6 -> 129.6
B21: Spread cost to lender (bps) | C21: =-C20*10000/Inputs!C8/Inputs!C21 -> -30.259164
B23: MFN PROTECTION
B24: MFN cushion (bps) | C24: 50
B25: Sunset (months) | C25: 12
B26: Prob. of issue at higher spread | C26: 0.3
B27: Avg incremental spread (bps) | C27: 100
B28: MFN uplift to lender (bps spread) | C28: =C26*MAX(0,C27-C24)*C25/12*0.5 -> 7.5

Sheet Restricted Payments
B1: RESTRICTED PAYMENTS BUNDLE
B3: STARTER BASKET (Day-1 American call)
B4: Starter basket size (EUR m) | C4: 100
B5: Probability of using (% of basket) | C5: 0.8
B6: Effective extraction (EUR m) | C6: =C4*C5 -> 80
B7: Spread cost to lender (bps) | C7: =-C6*10000/Inputs!C8/Inputs!C21 -> -18.678496
B8: Spread cost = present value of foregone collateral × required return
B10: LEVERAGE-BASED RP (Knock-in barrier)
B11: RP leverage threshold (x) | C11: 4.5
B12: Current leverage | C12: =Inputs!C10 -> 4.46899
B13: Distance to barrier (turns) | C13: =C12-C11 -> -0.031010041
B14: Prob. of usable RP capacity if barrier crossed | C14: =IF(C13<=0,$C$18,1-NORMSDIST(C13/(Inputs!C14*SQRT(5)))) -> 0.85
B15: Capacity if barrier hit (EUR m) | C15: 200
B16: Effective extraction (EUR m) | C16: =C14*C15*0.6 -> 102
B17: Spread cost to lender (bps) | C17: =-C16*10000/Inputs!C8/Inputs!C21 -> -23.815083
B18: Above-barrier crossing prob. (input) | C18: 0.85 | D18: Hardcoded prob. when currently above the RP leverage barrier
B19: BUILDER BASKET (Asian-style)
B20: CNI growth p.a. | C20: 0.05
B21: CNI / EBITDA | C21: 0.5
B22: Build rate (% of CNI) | C22: 0.5
B23: Cumulative CNI over tenor (EUR m) | C23: =Inputs!C9*C21*Inputs!C21*(1+C20*(Inputs!C21+1)/2) -> 4867.375
B24: Builder basket capacity (EUR m) | C24: =C23*C22 -> 2433.6875
B25: Leverage-gate damping (4.5x gate) | C25: =NORMSDIST((C11-Inputs!C10*0.85)/(Inputs!C14*SQRT(Inputs!C21)))*0.7 -> 0.6999691
B26: Damping = N((gate - opening×0.85)/(σ_EBITDA×√T)) × 0.7 (exercise prob); 0.85 = deleverage factor
B27: Effective extraction (EUR m) | C27: =C24*C25 -> 1703.506
B28: Spread cost to lender (bps) | C28: =-C27*10000/Inputs!C8/Inputs!C21 -> -397.73664
B30: RP BUNDLE TOTAL
B31: Total RP spread cost (bps) | C31: =C7+C17+C28 -> -440.23022

Sheet Asset Sale Bundle
B1: ASSET SALE OPTIONALITY
B3: REINVESTMENT RIGHT (real option, 365d window)
B4: Expected proceeds (EUR m) | C4: 100
B5: Probability of asset sale | C5: 0.4
B6: Strategic premium (% above debt PV) | C6: 0.1
B7: Value to borrower (EUR m) | C7: =C4*C5*C6 -> 4
B8: Spread cost to lender (bps) | C8: =-C7*10000/Inputs!C8/Inputs!C21 -> -0.93392482
B10: LEVERAGE STEP-DOWN
B11: Avg sweep retention (across thresholds) | C11: 0.5
B12: Avg proceeds re-deployed (EUR m) | C12: =C4*C5*(1-C11) -> 20
B13: Spread cost to lender (bps) | C13: =-C12*0.3*10000/Inputs!C8/Inputs!C21 -> -1.4008872
B14: Step-down cost = avoided sweep × marginal cost-of-capital

Sheet CoC & Portability
B1: CHANGE-OF-CONTROL PUT + PORTABILITY
B3: GROSS CoC PUT (101% strike)
B4: CoC hazard λ | C4: =Inputs!C26 -> 0.18
B5: Tenor | C5: =Inputs!C21 -> 5
B6: Cumulative CoC probability | C6: =1-EXP(-C4*C5) -> 0.59343034
B7: Bond duration (years) | C7: 4
B8: Put premium | C8: 0.01
B9: Gross CoC put PV (% of par) | C9: =C6*C8 -> 0.0059343034
B10: Gross CoC put as bps spread | C10: =C9*10000/C7 -> 14.835759
B12: PORTABILITY ADJUSTMENT
B13: Portability threshold (x) | C13: 4.5
B14: Current leverage | C14: =Inputs!C10 -> 4.46899
B15: Prob. pro-forma lev > threshold (put fires) | C15: 0.65
B16: Portability-adjusted put (bps) | C16: =C10*C15 -> 9.643243
B18: DISGUISED PORTABILITY (Permitted Holders)
B19: PH coverage of buyer universe | C19: =Inputs!C28 -> 0.4
B20: Net CoC put value to lender (bps) | C20: =C16*(1-C19) -> 5.7859458
B21: Total giveback (gross - net) | C21: =C10-C20 -> 9.0498127

Sheet Equity Cure
B1: EQUITY CURE RIGHT (Bermudan put, sponsor-side)
B3: INPUTS
B4: Number of cure rights | C4: 5
B5: Maintenance covenant (x) | C5: 5.75
B6: Avg cure injection per use (EUR m) | C6: 25
B7: Recovery improvement per cure | C7: 0.05
B8: Realistic: each cure improves expected recovery by ~5%, not 20%
B10: RESULTS
B11: Probability of covenant breach over tenor | C11: =MIN(0.6, NORMSDIST((Inputs!C10-C5)/(Inputs!C14*SQRT(Inputs!C21)))) -> 4.0029091e-13
B12: Expected cures used | C12: =MIN(C11*C4,C4*0.6) -> 2.0014546e-12
B13: PV of injections (EUR m) | C13: =C12*C6 -> 5.0036364e-11
B14: Recovery improvement (EUR m) | C14: =C12*Inputs!C6*C7 -> 6.1844946e-10
B15: Sponsor net option value (EUR m) | C15: =C14-C13 -> 5.6841309e-10
B16: Spread cost to lender (bps) | C16: =-C15*10000/Inputs!C8/Inputs!C21 -> -1.3271377e-10

Sheet Springing Cov + MFN
B1: SPRINGING COVENANT + MFN
B3: SPRINGING COVENANT (RCF knock-in)
B4: RCF utilization barrier | C4: 0.4
B5: Springing leverage threshold | C5: 5.75
B6: Prob. of barrier hit at QE | C6: 0.15
B7: Springing covenant value if springs (bps spread) | C7: 75
B8: Lender gain (bps spread) | C8: =C6*C7 -> 11.25
B10: MFN LOOKBACK (lender protection)
B11: MFN cushion (bps) | C11: 50
B12: Sunset (months) | C12: 12
B13: Prob. of MFN trigger | C13: 0.3
B14: Avg new-issue spread above existing (bps) | C14: 100
B15: Lender uplift (bps) | C15: =C13*MAX(0,C14-C11)*(C12/12)*0.5 -> 7.5

Sheet LME Bundle
B1: LME BUNDLE
B3: UPTIER EXCHANGE (Serta-style)
B4: Distress probability (5y cumulative) | C4: 0.2
B5: Recovery if primed (cents/dollar) | C5: 0.35
B6: Recovery if coordinated resistance | C6: 0.55
B7: Recovery if part of majority | C7: 0.7
B8: Anti-Serta strength (0-1) | C8: 0.8
B9: Recovery without anti-Serta | C9: =0.5*C5+0.5*C7 -> 0.525
B10: Recovery with anti-Serta | C10: =C8*C6+(1-C8)*C9 -> 0.545
B11: Recovery delta | C11: =C10-C9 -> 0.02
B12: PV improvement (EUR m) | C12: =C4*C11*Inputs!C6 -> 24.72
B13: Anti-Serta uplift to lender (bps) | C13: =C12*10000/Inputs!C8/Inputs!C21 -> 5.7716554
B15: DROP-DOWN (J.Crew)
B16: Anti-J.Crew strength | C16: 0.85
B17: Collateral leakage if no anti-J.Crew (% of V) | C17: 0.05
B18: Recovery improvement (EUR m) | C18: =C4*C16*C17*Inputs!C4 -> 154.649
B19: Anti-J.Crew uplift (bps) | C19: =C18*10000/Inputs!C8/Inputs!C21 -> 36.107635

Sheet Master Summary
B1: MASTER SUMMARY
B2: Aggregate borrower-side optionality (negative to lender). Compare to market spread.
B4: Option Component | C4: Value (bps) | D4: Side | E4: Base
B5: Credit-risk put (Merton, adjusted) | C5: =-'Merton Credit Put'!C27 -> -4.7641421e-06 | D5: Short | E5: Deal (total debt × tenor)
B6: Fixed call schedule (HY) | C6: ='Call Schedule (HY)'!C20*Inputs!C7/Inputs!C8 -> -1.2831793 | D6: Short | E6: HY → deal-weighted
B7: Make-whole option | C7: ='Call Schedule (HY)'!C25*Inputs!C7/Inputs!C8 -> -8.4946299 | D7: Short | E7: HY → deal-weighted
B8: Free-and-clear basket | C8: ='Debt Incurrence'!C9 -> -1.1236283 | D8: Short | E8: Deal (total debt × tenor)
B9: Ratio-based incremental | C9: ='Debt Incurrence'!C21 -> -30.259164 | D9: Short | E9: Deal (total debt × tenor)
B10: MFN protection uplift | C10: ='Debt Incurrence'!C28 -> 7.5 | D10: Long | E10: Deal (total debt × tenor)
B11: RP starter basket | C11: ='Restricted Payments'!C7 -> -18.678496 | D11: Short | E11: Deal (total debt × tenor)
B12: Leverage-based RP | C12: ='Restricted Payments'!C17 -> -23.815083 | D12: Short | E12: Deal (total debt × tenor)
B13: Builder basket (Asian) | C13: ='Restricted Payments'!C28 -> -397.73664 | D13: Short | E13: Deal (total debt × tenor)
B14: Asset-sale reinvestment | C14: ='Asset Sale Bundle'!C8 -> -0.93392482 | D14: Short | E14: Deal (total debt × tenor)
B15: Asset-sale step-down | C15: ='Asset Sale Bundle'!C13 -> -1.4008872 | D15: Short | E15: Deal (total debt × tenor)
B16: CoC put (net of portability) | C16: ='CoC & Portability'!C20*('CoC & Portability'!C7/Inputs!C21)*(Inputs!C7/Inputs!C8) -> 0.74894428 | D16: Long | E16: HY → deal-weighted
B17: Disguised portability giveback | C17: =-'CoC & Portability'!C21*('CoC & Portability'!C7/Inputs!C21)*(Inputs!C7/Inputs!C8) -> -1.1714257 | D17: Short | E17: HY → deal-weighted
B18: Equity cure | C18: ='Equity Cure'!C16 -> -1.3271377e-10 | D18: Short | E18: Deal (total debt × tenor)
B19: Springing covenant | C19: ='Springing Cov + MFN'!C8 -> 11.25 | D19: Long | E19: Deal (total debt × tenor)
B20: MFN lookback uplift | C20: ='Springing Cov + MFN'!C15 -> 7.5 | D20: Long | E20: Deal (total debt × tenor)
B21: Anti-Serta value | C21: ='LME Bundle'!C13 -> 5.7716554 | D21: Long | E21: Deal (total debt × tenor)
B22: Anti-J.Crew value | C22: ='LME Bundle'!C19 -> 36.107635 | D22: Long | E22: Deal (total debt × tenor)
B23: TOTAL NET OPTIONALITY (bps) | C23: =SUM(C5:C22) -> -416.01883
B25: Market spread (bps) | C25: =Inputs!C22 -> 248
B26: Pure credit-risk component (Merton adj.) | C26: ='Merton Credit Put'!C27 -> 4.7641421e-06
B27: Optionality cost embedded in spread | C27: =C25-C26 -> 248
B28: Model required spread for optionality (ex-Merton) | C28: =-(C23-C5) -> 416.01883
B29: Mispricing (market optionality - model optionality) | C29: =C27-C28 -> -168.01883
B31: Note (v2.1): all values normalised to annualised bps on Total Debt × Tenor.
B32: HY-only options (calls, CoC, portability) face-weighted by HY/Total Debt in this sheet.
B33: Cheap if Mispricing > 0 (market over-compensates); rich if < 0 (model values options higher).
B34: Parametric; canonical Grifols figures live in Grifols_Model_v8.xlsx.

Sheet Sensitivity
B1: ONE-WAY SENSITIVITY — Total Net Optionality (bps)
B2: Each row holds all other inputs at base, then flexes one input across the listed values. Cells show TOTAL NET OPTIONALITY in bps.
B4: Input flexed | C4: Low | D4: Mid-low | E4: Base | F4: Mid-high | G4: High | H4: Notes
B5: Enterprise Value (€m) | C5: -423.24361 | D5: -419.6309 | E5: -416.01883 | F5: -412.40886 | G5: -408.7969 | H5: Inputs!C4; sweeps: 14555, 16374, 18194, 20013, 21833
B6: LTM EBITDA (€m) | C6: -57.014023 | D6: -319.80033 | E6: -416.01883 | F6: -467.88381 | G6: -519.42625 | H6: Inputs!C9; sweeps: 1354, 1524, 1693, 1863, 2032
B7: Asset volatility σ_V | C7: -416.01883 | D7: -416.01883 | E7: -416.01883 | F7: -416.07794 | G7: -418.30846 | H7: Inputs!C13; sweeps: 0.04, 0.06, 0.08, 0.12, 0.16
B8: EBITDA volatility σ_EBITDA | C8: -416.03639 | D8: -416.03636 | E8: -416.01883 | F8: -414.25596 | G8: -406.15822 | H8: Inputs!C14; sweeps: 0.04, 0.06, 0.08, 0.12, 0.16
B9: Risk-free rate | C9: -416.01903 | D9: -416.01885 | E9: -416.01883 | F9: -416.01883 | G9: -416.01883 | H9: Inputs!C20; sweeps: 0.02, 0.035, 0.045, 0.055, 0.07
B10: Tenor (years) | C10: -422.55864 | D10: -416.32532 | E10: -416.01883 | F10: -418.64665 | G10: -422.90502 | H10: Inputs!C21; sweeps: 3, 4, 5, 6, 7
B11: Market TLB spread (bps) | C11: -416.01883 | D11: -416.01883 | E11: -416.01883 | F11: -416.01883 | G11: -416.01883 | H11: Inputs!C22; sweeps: 150, 200, 248, 300, 400
B12: CoC hazard (annual) | C12: -415.75383 | D12: -415.87647 | E12: -416.01883 | F12: -416.10431 | G12: -416.18457 | H12: Inputs!C26; sweeps: 0.05, 0.1, 0.18, 0.25, 0.35
B13: Permitted Holders coverage | C13: -415.51954 | D13: -415.76919 | E13: -416.01883 | F13: -416.39331 | G13: -416.76778 | H13: Inputs!C28; sweeps: 0.2, 0.3, 0.4, 0.55, 0.7
B15: Base case total: -416.02 bps
B16: Yellow cells highlight base-case values. All other cells flex one input.
